sandwitches/__init__.py
sandwitches/admin.py
sandwitches/api.py
sandwitches/asgi.py
sandwitches/feeds.py
sandwitches/forms.py
sandwitches/locale/nl/LC_MESSAGES/django.mo
sandwitches/locale/nl/LC_MESSAGES/django.po
sandwitches/management/__init__.py
sandwitches/management/commands/__init__.py
sandwitches/management/commands/reset_daily_orders.py
sandwitches/migrations/0001_initial.py
sandwitches/migrations/0002_historicalrecipe_servings_recipe_servings.py
sandwitches/migrations/0003_setting.py
sandwitches/migrations/0004_alter_setting_ai_api_key_and_more.py
sandwitches/migrations/0005_rating_comment.py
sandwitches/migrations/0006_historicalrecipe_is_highlighted_and_more.py
sandwitches/migrations/0007_historicalrecipe_price_recipe_price_order.py
sandwitches/migrations/0008_historicalrecipe_daily_orders_count_and_more.py
sandwitches/migrations/0009_historicalrecipe_is_approved_recipe_is_approved.py
sandwitches/migrations/0010_rename_is_approved_historicalrecipe_is_community_made_and_more.py
sandwitches/migrations/0011_alter_historicalrecipe_is_community_made_and_more.py
sandwitches/migrations/0012_rename_is_community_made_historicalrecipe_is_approved_and_more.py
sandwitches/migrations/0013_cartitem.py
sandwitches/migrations/0014_ensure_groups_exist.py
sandwitches/migrations/0015_order_completed_alter_order_status_and_more.py
sandwitches/migrations/0016_user_theme.py
sandwitches/migrations/0017_setting_gotify_token_setting_gotify_url.py
sandwitches/migrations/__init__.py
sandwitches/models.py
sandwitches/settings.py
sandwitches/storage.py
sandwitches/tasks.py
sandwitches/templates/admin/admin_base.html
sandwitches/templates/admin/confirm_delete.html
sandwitches/templates/admin/dashboard.html
sandwitches/templates/admin/order_list.html
sandwitches/templates/admin/partials/dashboard_charts.html
sandwitches/templates/admin/partials/order_rows.html
sandwitches/templates/admin/rating_list.html
sandwitches/templates/admin/recipe_approval_list.html
sandwitches-2.5.4.dist-info/WHEEL
sandwitches-2.5.4.dist-info/METADATA
sandwitches-2.5.4.dist-info/RECORD
