Metadata-Version: 2.3
Name: sandwitches
Version: 2.5.4
Summary: Add your description here
Author: Martyn van Dijke
Author-email: Martyn van Dijke <martijnvdijke600@gmail.com>
Requires-Dist: django-debug-toolbar>=6.1.0
Requires-Dist: django-filter>=25.2
Requires-Dist: django-imagekit>=6.0.0
Requires-Dist: django-import-export>=4.3.14
Requires-Dist: django-ninja>=1.5.1
Requires-Dist: django-simple-history>=3.10.1
Requires-Dist: django-tasks>=0.10.0
Requires-Dist: django-solo>=2.3.0
Requires-Dist: django>=6.0.0
Requires-Dist: gunicorn>=23.0.0
Requires-Dist: markdown>=3.10
Requires-Dist: pillow>=12.0.0
Requires-Dist: uvicorn>=0.40.0
Requires-Dist: whitenoise[brotli]>=6.11.0
Requires-Dist: requests>=2.32.5
Requires-Python: >=3.12
